pysc2/__init__.py
pysc2/agents/__init__.py
pysc2/agents/base_agent.py
pysc2/agents/no_op_agent.py
pysc2/agents/random_agent.py
pysc2/agents/scripted_agent.py
pysc2/bin/__init__.py
pysc2/bin/agent.py
pysc2/bin/agent_remote.py
pysc2/bin/battle_net_maps.py
pysc2/bin/benchmark_observe.py
pysc2/bin/benchmark_replay.py
pysc2/bin/check_apm.py
pysc2/bin/compare_binaries.py
pysc2/bin/gen_actions.py
pysc2/bin/gen_data.py
pysc2/bin/gen_versions.py
pysc2/bin/map_list.py
pysc2/bin/mem_leak_check.py
pysc2/bin/play.py
pysc2/bin/play_vs_agent.py
pysc2/bin/reencode_replays.py
pysc2/bin/replay_actions.py
pysc2/bin/replay_info.py
pysc2/bin/replay_version.py
pysc2/bin/run_tests.py
pysc2/bin/update_battle_net_cache.py
pysc2/bin/valid_actions.py
pysc2/env/__init__.py
pysc2/env/available_actions_printer.py
pysc2/env/base_env_wrapper.py
pysc2/env/converted_env.py
pysc2/env/converted_env_test.py
pysc2/env/enums.py
pysc2/env/environment.py
pysc2/env/host_remote_agent.py
pysc2/env/lan_sc2_env.py
pysc2/env/mock_sc2_env.py
pysc2/env/mock_sc2_env_comparison_test.py
pysc2/env/mock_sc2_env_test.py
pysc2/env/remote_sc2_env.py
pysc2/env/run_loop.py
pysc2/env/sc2_env.py
pysc2/env/sc2_env_test.py
pysc2/lib/__init__.py
pysc2/lib/actions.py
pysc2/lib/buffs.py
pysc2/lib/colors.py
pysc2/lib/features.py
pysc2/lib/features_test.py
pysc2/lib/gfile.py
pysc2/lib/image_differencer.py
pysc2/lib/image_differencer_test.py
pysc2/lib/memoize.py
pysc2/lib/metrics.py
pysc2/lib/named_array.py
pysc2/lib/named_array_test.py
pysc2/lib/np_util.py
pysc2/lib/np_util_test.py
pysc2/lib/point.py
pysc2/lib/point_flag.py
pysc2/lib/point_test.py
pysc2/lib/portspicker.py
pysc2/lib/portspicker_test.py
pysc2/lib/proto_diff.py
pysc2/lib/proto_diff_test.py
pysc2/lib/protocol.py
pysc2/lib/remote_controller.py
pysc2/lib/renderer_ascii.py
pysc2/lib/renderer_human.py
pysc2/lib/replay.py
pysc2/lib/resources.py
pysc2/lib/run_parallel.py
pysc2/lib/run_parallel_test.py
pysc2/lib/sc_process.py
pysc2/lib/static_data.py
pysc2/lib/stopwatch.py
PySC2-4.0.0.dist-info/LICENSE
PySC2-4.0.0.dist-info/METADATA
PySC2-4.0.0.dist-info/WHEEL
PySC2-4.0.0.dist-info/entry_points.txt
PySC2-4.0.0.dist-info/top_level.txt
PySC2-4.0.0.dist-info/RECORD
