Metadata-Version: 2.1
Name: PySC2
Version: 4.0.0
Summary: Starcraft II environment and library for training agents.
Home-page: https://github.com/deepmind/pysc2
Author: DeepMind
Author-email: pysc2@deepmind.com
License: Apache License, Version 2.0
Keywords: StarCraft AI
Platform: UNKNOWN
Classifier: Development Status :: 4 - Beta
Classifier: Environment :: Console
Classifier: Intended Audience :: Science/Research
Classifier: License :: OSI Approved :: Apache Software License
Classifier: Operating System :: POSIX :: Linux
Classifier: Operating System :: Microsoft :: Windows
Classifier: Operating System :: MacOS :: MacOS X
Classifier: Programming Language :: Python :: 3.8
Classifier: Programming Language :: Python :: 3.9
Classifier: Programming Language :: Python :: 3.10
Classifier: Topic :: Scientific/Engineering :: Artificial Intelligence
License-File: LICENSE
Requires-Dist: absl-py (>=0.1.0)
Requires-Dist: deepdiff
Requires-Dist: dm-env
Requires-Dist: enum34
Requires-Dist: mock
Requires-Dist: mpyq
Requires-Dist: numpy (>=1.10)
Requires-Dist: portpicker (>=1.2.0)
Requires-Dist: protobuf (>=2.6)
Requires-Dist: pygame
Requires-Dist: requests
Requires-Dist: s2clientprotocol (>=4.10.1.75800.0)
Requires-Dist: s2protocol
Requires-Dist: sk-video
Requires-Dist: websocket-client
